wush/__init__.py
wush/__version__.py
wush/argument/__init__.py
wush/argument/alias.py
wush/argument/command.py
wush/argument/config.py
wush/argument/cookie.py
wush/argument/default.py
wush/argument/env.py
wush/argument/func.py
wush/argument/history.py
wush/argument/run.py
wush/argument/server.py
wush/argument/shell.py
wush/argument/view.py
wush/cli/__init__.py
wush/cli/command.py
wush/cli/exceptions.py
wush/cli/main.py
wush/cli/run.py
wush/cli/server.py
wush/cli/shell.py
wush/cli/test.py
wush/common/__init__.py
wush/common/config_value.py
wush/common/constants.py
wush/common/dicts.py
wush/common/exceptions.py
wush/common/loggers.py
wush/common/run_mode.py
wush/common/utils.py
wush/completion/__init__.py
wush/completion/base.py
wush/completion/command.py
wush/completion/filesystem.py
wush/completion/word.py
wush/config/__init__.py
wush/config/config.py
wush/config/config.yml
wush/config/function.py
wush/config/models.py
wush/web/__init__.py
wush/web/cookie.py
wush/web/curl.py
wush/web/curl_utils.py
wush/web/enums.py
wush/web/history.py
wush/web/models.py
wush/web/request.py
wush/web/response.py
wush/web/routing.py
wush/web/utils.py
wush-0.2.3.dist-info/entry_points.txt
wush-0.2.3.dist-info/LICENSE
wush-0.2.3.dist-info/WHEEL
wush-0.2.3.dist-info/METADATA
wush-0.2.3.dist-info/RECORD
