Metadata-Version: 2.1
Name: wush
Version: 0.2.3
Summary: Useful api client on terminal
License: MIT
Author: wxnacy
Author-email: wxnacy@gmail.com
Requires-Python: >=3.6.2,<4.0.0
Classifier: License :: OSI Approved :: MIT License
Classifier: Programming Language :: Python :: 3
Classifier: Programming Language :: Python :: 3.10
Classifier: Programming Language :: Python :: 3.7
Classifier: Programming Language :: Python :: 3.8
Classifier: Programming Language :: Python :: 3.9
Requires-Dist: Flask (>=2.0.1,<3.0.0)
Requires-Dist: PyYAML (>=6.0,<7.0)
Requires-Dist: browsercookie (>=0.7.7,<0.8.0)
Requires-Dist: csarg (>=0.1.0,<0.2.0)
Requires-Dist: loguru (>=0.6.0,<0.7.0)
Requires-Dist: prompt-toolkit (>=3.0.29,<4.0.0)
Requires-Dist: pydantic (>=1.9.0,<2.0.0)
Requires-Dist: requests (>=2.27.1,<3.0.0)
Requires-Dist: rich (>=10.6.0,<11.0.0)
Requires-Dist: w3lib (>=1.22.0,<2.0.0)
Requires-Dist: wpy (>=0.6.1,<0.7.0)
